LICENSE
MANIFEST.in
README.md
setup.cfg
setup.py
versioneer.py
bin/KNe_stdcandle.py
bin/KNe_stdcandle_GRB.py
bin/KNe_stdcandle_GRB_GW.py
bin/KNe_stdcandle_GRB_GW_Bulla.py
bin/KNe_stdcandle_GRB_GW_combined.py
bin/KNe_stdcandle_GRB_combined.py
bin/KNe_stdcandle_combined.py
bin/KNe_stdcandle_combined_Kasen_Bulla.py
bin/KNe_stdcandle_combined_errorbudget.py
bin/KNe_stdcandle_combined_inferred.py
bin/KNe_stdcandle_combined_systematics.py
bin/KNe_stdcandle_comparison.py
bin/KNe_stdcandle_ejecta_fits.py
bin/analyze_lightcurves.py
bin/plot_afterglow_models_GRB.py
bin/plot_eos.py
bin/plot_fitting_models.py
bin/plot_highenergy.py
bin/plot_joint_models_GW170817.py
bin/plot_lightcurves_GRB.py
bin/plot_lightcurves_event.py
bin/plot_lightcurves_inclination.py
bin/plot_lightcurves_models.py
bin/plot_lightcurves_models_GRB050709.py
bin/plot_lightcurves_models_GRB051221A.py
bin/plot_lightcurves_models_GRB060614.py
bin/plot_lightcurves_models_GRB130603B.py
bin/plot_lightcurves_models_GRB140903A.py
bin/plot_lightcurves_models_GRB150101B.py
bin/plot_lightcurves_models_GRB160821B.py
bin/plot_lightcurves_models_GRB170817A.py
bin/plot_lightcurves_models_GW170817.py
bin/plot_lightcurves_spectra_models_GW170817.py
bin/plot_luminosity_models_GW170817.py
bin/plot_masses_models_GRB.py
bin/plot_models.py
bin/plot_models_ATLAS18qqn.py
bin/plot_models_hst.py
bin/plot_models_lcogt.py
bin/plot_parameterized_models.py
bin/plot_peaktime_GRB.py
bin/plot_spec.py
bin/plot_spec_models_GW170817.py
bin/renameBulla.py
bin/run_ATLAS.sh
bin/run_fitting_models.py
bin/run_lightcurves.py
bin/run_lightcurves_logL.py
bin/run_lightcurves_models.py
bin/run_luminosity_models.py
bin/run_models.py
bin/run_parameterized_models.py
bin/run_parameterized_models_event.py
bin/run_run_lightcurves.py
bin/run_run_lightcurves_models.py
bin/run_run_lightcurves_models_ATLAS18qqn.py
bin/run_run_lightcurves_models_G298048.py
bin/run_run_lightcurves_models_GRB.py
bin/run_run_lightcurves_models_GRB051221A.py
gwemlightcurves.egg-info/PKG-INFO
gwemlightcurves.egg-info/SOURCES.txt
gwemlightcurves.egg-info/dependency_links.txt
gwemlightcurves.egg-info/requires.txt
gwemlightcurves.egg-info/top_level.txt
